petprep_docker/__init__.py
petprep_docker/__main__.py
petprep_docker/_version.py
petprep_docker-0.0.2.dist-info/METADATA
petprep_docker-0.0.2.dist-info/WHEEL
petprep_docker-0.0.2.dist-info/entry_points.txt
petprep_docker-0.0.2.dist-info/licenses/LICENSE
petprep_docker-0.0.2.dist-info/RECORD
