Metadata-Version: 2.4
Name: petprep-docker
Version: 0.0.2
Summary: A wrapper for generating Docker commands using regular PETPrep syntax
Project-URL: Homepage, https://github.com/nipreps/petprep
Project-URL: Documentation, https://petprep.readthedocs.io
Project-URL: Paper, https://doi.org/10.1038/s41592-018-0235-4
Project-URL: Docker Images, https://hub.docker.com/r/nipreps/petprep/tags/
Project-URL: NiPreps, https://www.nipreps.org/
Author-email: The NiPreps Developers <nipreps@gmail.com>
License: Copyright (c) the Nipreps developers.
License-File: LICENSE
Classifier: Development Status :: 5 - Production/Stable
Classifier: Intended Audience :: Science/Research
Classifier: License :: OSI Approved :: Apache Software License
Classifier: License :: OSI Approved :: BSD License
Classifier: Programming Language :: Python :: 2.7
Classifier: Programming Language :: Python :: 3.5
Classifier: Programming Language :: Python :: 3.6
Classifier: Programming Language :: Python :: 3.7
Classifier: Programming Language :: Python :: 3.8
Classifier: Programming Language :: Python :: 3.9
Classifier: Programming Language :: Python :: 3.10
Classifier: Topic :: Scientific/Engineering :: Image Recognition
Requires-Python: >=2.7
